bonaparte/__init__.py
bonaparte/const.py
bonaparte/device.py
bonaparte/exceptions.py
bonaparte/fireplace.py
bonaparte/parser.py
bonaparte/py.typed
bonaparte/utils.py
bonaparte-1.0.1.dist-info/WHEEL
bonaparte-1.0.1.dist-info/METADATA
bonaparte-1.0.1.dist-info/RECORD
