Metadata-Version: 2.4
Name: bonaparte
Version: 1.0.1
Summary: Library to control Napoleon eFIRE enabled fireplaces
Author: Felix Kaechele
Author-email: Felix Kaechele <felix@kaechele.ca>
License-Expression: MIT
Classifier: Development Status :: 4 - Beta
Classifier: Intended Audience :: Developers
Classifier: Natural Language :: English
Classifier: Operating System :: OS Independent
Classifier: Topic :: Home Automation
Classifier: Topic :: Software Development :: Libraries
Requires-Dist: bleak>=1.0.0
Requires-Dist: bleak-retry-connector>=4.0.0
Requires-Python: >=3.13, <3.14
Project-URL: Bug Tracker, https://github.com/kaechele/bonaparte/issues
Project-URL: Changelog, https://github.com/kaechele/bonaparte/blob/main/CHANGELOG.md
Project-URL: Documentation, https://bonaparte.readthedocs.io
Project-URL: Repository, https://github.com/kaechele/bonaparte
